.version 50 0
.source FtpServerHandler.java
.class public super com/alexkasko/netty/ftp/FtpServerHandler
.super [_3]

.field private static final logger Lorg/slf4j/Logger;
.field private static final CR B = 13
.field private static final LF B = 10
.field private static final CRLF [B
.field private static final ASCII Ljava/nio/charset/Charset;
.field private final receiver Lcom/alexkasko/netty/ftp/DataReceiver;
.field private final passiveAddress [B
.field private final lowestPassivePort I
.field private final highestPassivePort I
.field private final passiveOpenAttempts I
.field private curDir Ljava/lang/String;
.field private lastCommand Ljava/lang/String;
.field private activeSocket Ljava/net/Socket;
.field private passiveSocket Ljava/net/ServerSocket;

.method static <clinit> : ()V
	.limit stack 4
	.limit locals 0
	ldc [_1]
	invokestatic org/slf4j/LoggerFactory getLogger (Ljava/lang/Class;)Lorg/slf4j/Logger;
	putstatic com/alexkasko/netty/ftp/FtpServerHandler logger Lorg/slf4j/Logger;
	iconst_2
	newarray byte
	dup
	iconst_0
	bipush 13
	bastore
	dup
	iconst_1
	bipush 10
	bastore
	putstatic com/alexkasko/netty/ftp/FtpServerHandler CRLF [B
	ldc 'ASCII'
	invokestatic java/nio/charset/Charset forName (Ljava/lang/String;)Ljava/nio/charset/Charset;
	putstatic com/alexkasko/netty/ftp/FtpServerHandler ASCII Ljava/nio/charset/Charset;
	return
.end method

.method public <init> : (Lcom/alexkasko/netty/ftp/DataReceiver;)V
	.limit stack 6
	.limit locals 2
	aload_0
	aload_1
	iconst_4
	newarray byte
	dup
	iconst_0
	bipush 127
	bastore
	dup
	iconst_3
	iconst_1
	bastore
	sipush 2121
	sipush 4242
	bipush 10
	invokespecial com/alexkasko/netty/ftp/FtpServerHandler <init> (Lcom/alexkasko/netty/ftp/DataReceiver;[BIII)V
	return
.end method

.method public <init> : [_62]
	.limit stack 6
	.limit locals 6
	aload_0
	aload_1
	aload_2
	invokevirtual java/net/InetAddress getAddress ()[B
	iload_3
	iload 4
	iload 5
	invokespecial com/alexkasko/netty/ftp/FtpServerHandler <init> (Lcom/alexkasko/netty/ftp/DataReceiver;[BIII)V
	return
.end method

.method public <init> : (Lcom/alexkasko/netty/ftp/DataReceiver;[BIII)V
	.limit stack 5
	.limit locals 6
	aload_0
	invokespecial [_3] <init> ()V
	aload_0
	ldc '/'
	putfield com/alexkasko/netty/ftp/FtpServerHandler curDir Ljava/lang/String;
	aload_0
	ldc ''
	putfield com/alexkasko/netty/ftp/FtpServerHandler lastCommand Ljava/lang/String;
	aload_0
	aconst_null
	putfield com/alexkasko/netty/ftp/FtpServerHandler activeSocket Ljava/net/Socket;
	aload_0
	aconst_null
	putfield com/alexkasko/netty/ftp/FtpServerHandler passiveSocket Ljava/net/ServerSocket;
	aload_1
	ifnonnull L40
	new java/lang/IllegalArgumentException
	dup
	ldc 'Provided receiver is null'
	invokespecial java/lang/IllegalArgumentException <init> (Ljava/lang/String;)V
	athrow
L40:
.stack full
	locals Object com/alexkasko/netty/ftp/FtpServerHandler Object com/alexkasko/netty/ftp/DataReceiver Object [B Integer Integer Integer
	stack 
.end stack
	aload_0
	aload_1
	putfield com/alexkasko/netty/ftp/FtpServerHandler receiver Lcom/alexkasko/netty/ftp/DataReceiver;
	aload_2
	ifnonnull L59
	new java/lang/IllegalArgumentException
	dup
	ldc 'Provided passiveAddress is null'
	invokespecial java/lang/IllegalArgumentException <init> (Ljava/lang/String;)V
	athrow
L59:
.stack same
	aload_0
	aload_2
	putfield com/alexkasko/netty/ftp/FtpServerHandler passiveAddress [B
	iload_3
	ifle L74
	iload_3
	ldc 65536
	if_icmplt L103
L74:
.stack same
	new java/lang/IllegalArgumentException
	dup
	new java/lang/StringBuilder
	dup
	ldc 'Provided lowestPassivePort: ['
	invokespecial java/lang/StringBuilder <init> (Ljava/lang/String;)V
	iload_3
	invokevirtual java/lang/StringBuilder append (I)Ljava/lang/StringBuilder;
	ldc '] ia out of valid range'
	invokevirtual java/lang/StringBuilder append (Ljava/lang/String;)Ljava/lang/StringBuilder;
	invokevirtual java/lang/StringBuilder toString ()Ljava/lang/String;
	invokespecial java/lang/IllegalArgumentException <init> (Ljava/lang/String;)V
	athrow
L103:
.stack same
	iload 4
	ifle L115
	iload 4
	ldc 65536
	if_icmplt L145
L115:
.stack same
	new java/lang/IllegalArgumentException
	dup
	new java/lang/StringBuilder
	dup
	ldc 'Provided highestPassivePort: ['
	invokespecial java/lang/StringBuilder <init> (Ljava/lang/String;)V
	iload 4
	invokevirtual java/lang/StringBuilder append (I)Ljava/lang/StringBuilder;
	ldc '] ia out of valid range'
	invokevirtual java/lang/StringBuilder append (Ljava/lang/String;)Ljava/lang/StringBuilder;
	invokevirtual java/lang/StringBuilder toString ()Ljava/lang/String;
	invokespecial java/lang/IllegalArgumentException <init> (Ljava/lang/String;)V
	athrow
L145:
.stack same
	iload_3
	iload 4
	if_icmple L195
	new java/lang/IllegalArgumentException
	dup
	new java/lang/StringBuilder
	dup
	ldc 'Provided lowestPassivePort: ['
	invokespecial java/lang/StringBuilder <init> (Ljava/lang/String;)V
	iload_3
	invokevirtual java/lang/StringBuilder append (I)Ljava/lang/StringBuilder;
	ldc '] must be not greater than '
	invokevirtual java/lang/StringBuilder append (Ljava/lang/String;)Ljava/lang/StringBuilder;
	ldc 'highestPassivePort: ['
	invokevirtual java/lang/StringBuilder append (Ljava/lang/String;)Ljava/lang/StringBuilder;
	iload 4
	invokevirtual java/lang/StringBuilder append (I)Ljava/lang/StringBuilder;
	ldc ']'
	invokevirtual java/lang/StringBuilder append (Ljava/lang/String;)Ljava/lang/StringBuilder;
	invokevirtual java/lang/StringBuilder toString ()Ljava/lang/String;
	invokespecial java/lang/IllegalArgumentException <init> (Ljava/lang/String;)V
	athrow
L195:
.stack same
	aload_0
	iload_3
	putfield com/alexkasko/netty/ftp/FtpServerHandler lowestPassivePort I
	aload_0
	iload 4
	putfield com/alexkasko/netty/ftp/FtpServerHandler highestPassivePort I
	iload 5
	ifgt L241
	new java/lang/IllegalArgumentException
	dup
	new java/lang/StringBuilder
	dup
	ldc 'Provided passiveOpenAttempts: ['
	invokespecial java/lang/StringBuilder <init> (Ljava/lang/String;)V
	iload 5
	invokevirtual java/lang/StringBuilder append (I)Ljava/lang/StringBuilder;
	ldc '] must be positive'
	invokevirtual java/lang/StringBuilder append (Ljava/lang/String;)Ljava/lang/StringBuilder;
	invokevirtual java/lang/StringBuilder toString ()Ljava/lang/String;
	invokespecial java/lang/IllegalArgumentException <init> (Ljava/lang/String;)V
	athrow
L241:
.stack same
	aload_0
	iload 5
	putfield com/alexkasko/netty/ftp/FtpServerHandler passiveOpenAttempts I
	return
.end method

.method public messageReceived : [_139]
.throws java/lang/Exception
	.limit stack 4
	.limit locals 6
	aload_2
	invokeinterface org/jboss/netty/channel/MessageEvent getMessage ()Ljava/lang/Object; 1
	checkcast java/lang/String
	invokevirtual java/lang/String trim ()Ljava/lang/String;
	astore_3
	aload_3
	invokevirtual java/lang/String length ()I
	iconst_3
	if_icmpge L30
	ldc '501 Syntax error'
	aload_1
	aload_3
	ldc ''
	invokestatic com/alexkasko/netty/ftp/FtpServerHandler send [_163]
L30:
.stack append
	locals Object java/lang/String
.end stack
	iconst_3
	aload_3
	invokevirtual java/lang/String length ()I
	if_icmpne L47
	aload_3
	iconst_0
	iconst_3
	invokevirtual java/lang/String substring (II)Ljava/lang/String;
	goto L56
L47:
.stack same
	aload_3
	iconst_0
	iconst_4
	invokevirtual java/lang/String substring (II)Ljava/lang/String;
	invokevirtual java/lang/String trim ()Ljava/lang/String;
L56:
.stack same_locals_1_stack_item
	stack Object java/lang/String
.end stack
	astore 4
	aload_3
	invokevirtual java/lang/String length ()I
	aload 4
	invokevirtual java/lang/String length ()I
	if_icmple L84
	aload_3
	aload 4
	invokevirtual java/lang/String length ()I
	iconst_1
	iadd
	invokevirtual java/lang/String substring (I)Ljava/lang/String;
	goto L86
L84:
.stack append
	locals Object java/lang/String
.end stack
	ldc ''
L86:
.stack same_locals_1_stack_item
	stack Object java/lang/String
.end stack
	astore 5
	ldc 'USER'
	aload 4
	invokevirtual java/lang/String equals (Ljava/lang/Object;)Z
	ifeq L111
	ldc '230 USER LOGGED IN'
	aload_1
	aload 4
	aload 5
	invokestatic com/alexkasko/netty/ftp/FtpServerHandler send [_163]
	goto L516
L111:
.stack append
	locals Object java/lang/String
.end stack
	ldc 'CWD'
	aload 4
	invokevirtual java/lang/String equals (Ljava/lang/Object;)Z
	ifeq L140
	aload_0
	aload 5
	putfield com/alexkasko/netty/ftp/FtpServerHandler curDir Ljava/lang/String;
	ldc '250 CWD command successful'
	aload_1
	aload 4
	aload 5
	invokestatic com/alexkasko/netty/ftp/FtpServerHandler send [_163]
	goto L516
L140:
.stack same
	ldc 'PWD'
	aload 4
	invokevirtual java/lang/String equals (Ljava/lang/Object;)Z
	ifeq L185
	new java/lang/StringBuilder
	dup
	ldc '257 "'
	invokespecial java/lang/StringBuilder <init> (Ljava/lang/String;)V
	aload_0
	getfield com/alexkasko/netty/ftp/FtpServerHandler curDir Ljava/lang/String;
	invokevirtual java/lang/StringBuilder append (Ljava/lang/String;)Ljava/lang/StringBuilder;
	ldc '" is current directory'
	invokevirtual java/lang/StringBuilder append (Ljava/lang/String;)Ljava/lang/StringBuilder;
	invokevirtual java/lang/StringBuilder toString ()Ljava/lang/String;
	aload_1
	aload 4
	aload 5
	invokestatic com/alexkasko/netty/ftp/FtpServerHandler send [_163]
	goto L516
L185:
.stack same
	ldc 'MKD'
	aload 4
	invokevirtual java/lang/String equals (Ljava/lang/Object;)Z
	ifeq L228
	new java/lang/StringBuilder
	dup
	ldc '521 "'
	invokespecial java/lang/StringBuilder <init> (Ljava/lang/String;)V
	aload 5
	invokevirtual java/lang/StringBuilder append (Ljava/lang/String;)Ljava/lang/StringBuilder;
	ldc '" directory exists'
	invokevirtual java/lang/StringBuilder append (Ljava/lang/String;)Ljava/lang/StringBuilder;
	invokevirtual java/lang/StringBuilder toString ()Ljava/lang/String;
	aload_1
	aload 4
	aload 5
	invokestatic com/alexkasko/netty/ftp/FtpServerHandler send [_163]
	goto L516
L228:
.stack same
	ldc 'DELE'
	aload 4
	invokevirtual java/lang/String equals (Ljava/lang/Object;)Z
	ifeq L271
	new java/lang/StringBuilder
	dup
	ldc '550 '
	invokespecial java/lang/StringBuilder <init> (Ljava/lang/String;)V
	aload 5
	invokevirtual java/lang/StringBuilder append (Ljava/lang/String;)Ljava/lang/StringBuilder;
	ldc ': no such file or directory'
	invokevirtual java/lang/StringBuilder append (Ljava/lang/String;)Ljava/lang/StringBuilder;
	invokevirtual java/lang/StringBuilder toString ()Ljava/lang/String;
	aload_1
	aload 4
	aload 5
	invokestatic com/alexkasko/netty/ftp/FtpServerHandler send [_163]
	goto L516
L271:
.stack same
	ldc 'RMD'
	aload 4
	invokevirtual java/lang/String equals (Ljava/lang/Object;)Z
	ifeq L314
	new java/lang/StringBuilder
	dup
	ldc '550 '
	invokespecial java/lang/StringBuilder <init> (Ljava/lang/String;)V
	aload 5
	invokevirtual java/lang/StringBuilder append (Ljava/lang/String;)Ljava/lang/StringBuilder;
	ldc ': no such file or directory'
	invokevirtual java/lang/StringBuilder append (Ljava/lang/String;)Ljava/lang/StringBuilder;
	invokevirtual java/lang/StringBuilder toString ()Ljava/lang/String;
	aload_1
	aload 4
	aload 5
	invokestatic com/alexkasko/netty/ftp/FtpServerHandler send [_163]
	goto L516
L314:
.stack same
	ldc 'RNFR'
	aload 4
	invokevirtual java/lang/String equals (Ljava/lang/Object;)Z
	ifeq L337
	ldc '350 File exists, ready for destination name'
	aload_1
	aload 4
	aload 5
	invokestatic com/alexkasko/netty/ftp/FtpServerHandler send [_163]
	goto L516
L337:
.stack same
	ldc 'RNTO'
	aload 4
	invokevirtual java/lang/String equals (Ljava/lang/Object;)Z
	ifeq L360
	ldc '250 RNTO command successful'
	aload_1
	aload 4
	aload 5
	invokestatic com/alexkasko/netty/ftp/FtpServerHandler send [_163]
	goto L516
L360:
.stack same
	ldc 'SYST'
	aload 4
	invokevirtual java/lang/String equals (Ljava/lang/Object;)Z
	ifeq L383
	ldc '215 UNIX Type: Java custom implementation'
	aload_1
	aload 4
	aload 5
	invokestatic com/alexkasko/netty/ftp/FtpServerHandler send [_163]
	goto L516
L383:
.stack same
	ldc 'NOOP'
	aload 4
	invokevirtual java/lang/String equals (Ljava/lang/Object;)Z
	ifeq L406
	ldc '200 OK'
	aload_1
	aload 4
	aload 5
	invokestatic com/alexkasko/netty/ftp/FtpServerHandler send [_163]
	goto L516
L406:
.stack same
	ldc 'TYPE'
	aload 4
	invokevirtual java/lang/String equals (Ljava/lang/Object;)Z
	ifeq L426
	aload_0
	aload_1
	aload 5
	invokevirtual com/alexkasko/netty/ftp/FtpServerHandler type [_224]
	goto L516
L426:
.stack same
	ldc 'PORT'
	aload 4
	invokevirtual java/lang/String equals (Ljava/lang/Object;)Z
	ifeq L446
	aload_0
	aload_1
	aload 5
	invokevirtual com/alexkasko/netty/ftp/FtpServerHandler port [_224]
	goto L516
L446:
.stack same
	ldc 'PASV'
	aload 4
	invokevirtual java/lang/String equals (Ljava/lang/Object;)Z
	ifeq L466
	aload_0
	aload_1
	aload 5
	invokevirtual com/alexkasko/netty/ftp/FtpServerHandler pasv [_224]
	goto L516
L466:
.stack same
	ldc 'LIST'
	aload 4
	invokevirtual java/lang/String equals (Ljava/lang/Object;)Z
	ifeq L486
	aload_0
	aload_1
	aload 5
	invokevirtual com/alexkasko/netty/ftp/FtpServerHandler list [_224]
	goto L516
L486:
.stack same
	ldc 'STOR'
	aload 4
	invokevirtual java/lang/String equals (Ljava/lang/Object;)Z
	ifeq L506
	aload_0
	aload_1
	aload 5
	invokevirtual com/alexkasko/netty/ftp/FtpServerHandler stor [_224]
	goto L516
L506:
.stack same
	ldc '500 Command unrecognized'
	aload_1
	aload 4
	aload 5
	invokestatic com/alexkasko/netty/ftp/FtpServerHandler send [_163]
L516:
.stack same
	aload_0
	aload 4
	putfield com/alexkasko/netty/ftp/FtpServerHandler lastCommand Ljava/lang/String;
	return
.end method

.method public exceptionCaught : [_255]
.throws java/lang/Exception
	.limit stack 4
	.limit locals 3
	getstatic com/alexkasko/netty/ftp/FtpServerHandler logger Lorg/slf4j/Logger;
	ldc_w 'Exception caught in FtpServerHandler'
	aload_2
	invokeinterface org/jboss/netty/channel/ExceptionEvent getCause ()Ljava/lang/Throwable; 1
	invokeinterface org/slf4j/Logger error (Ljava/lang/String;Ljava/lang/Throwable;)V 3
	ldc_w '500 Unspecified error'
	aload_1
	aload_2
	invokeinterface org/jboss/netty/channel/ExceptionEvent getCause ()Ljava/lang/Throwable; 1
	invokevirtual java/lang/Throwable getMessage ()Ljava/lang/String;
	ldc ''
	invokestatic com/alexkasko/netty/ftp/FtpServerHandler send [_163]
	return
.end method

.method public channelConnected : [_278]
.throws java/lang/Exception
	.limit stack 4
	.limit locals 3
	ldc_w '220 Service ready'
	aload_1
	ldc_w '[connected]'
	ldc ''
	invokestatic com/alexkasko/netty/ftp/FtpServerHandler send [_163]
	return
.end method

.method protected type : [_224]
	.limit stack 4
	.limit locals 3
	ldc_w 'I'
	aload_2
	invokevirtual java/lang/String equals (Ljava/lang/Object;)Z
	ifeq L23
	ldc_w '200 Type set to IMAGE NONPRINT'
	aload_1
	ldc 'TYPE'
	aload_2
	invokestatic com/alexkasko/netty/ftp/FtpServerHandler send [_163]
	goto L56
L23:
.stack same
	ldc_w 'A'
	aload_2
	invokevirtual java/lang/String equals (Ljava/lang/Object;)Z
	ifeq L46
	ldc_w '200 Type set to ASCII NONPRINT'
	aload_1
	ldc 'TYPE'
	aload_2
	invokestatic com/alexkasko/netty/ftp/FtpServerHandler send [_163]
	goto L56
L46:
.stack same
	ldc_w '504 Command not implemented for that parameter'
	aload_1
	ldc 'TYPE'
	aload_2
	invokestatic com/alexkasko/netty/ftp/FtpServerHandler send [_163]
L56:
.stack same
	return
.end method

.method protected port : [_224]
	.limit stack 5
	.limit locals 5
	.catch java/io/IOException from L75 to L104 using L107
	aload_2
	invokestatic com/alexkasko/netty/ftp/FtpServerHandler parsePortArgs (Ljava/lang/String;)Ljava/net/InetSocketAddress;
	astore_3
	getstatic com/alexkasko/netty/ftp/FtpServerHandler logger Lorg/slf4j/Logger;
	invokeinterface org/slf4j/Logger isTraceEnabled ()Z 1
	ifeq L28
	getstatic com/alexkasko/netty/ftp/FtpServerHandler logger Lorg/slf4j/Logger;
	aload_3
	invokestatic java/lang/String valueOf (Ljava/lang/Object;)Ljava/lang/String;
	invokeinterface org/slf4j/Logger trace (Ljava/lang/String;)V 2
L28:
.stack append
	locals Object java/net/InetSocketAddress
.end stack
	aload_3
	ifnonnull L45
	ldc_w '501 Syntax error in parameters or arguments'
	aload_1
	ldc 'PORT'
	aload_2
	invokestatic com/alexkasko/netty/ftp/FtpServerHandler send [_163]
	goto L155
L45:
.stack same
	aload_0
	getfield com/alexkasko/netty/ftp/FtpServerHandler activeSocket Ljava/net/Socket;
	ifnull L75
	aload_0
	getfield com/alexkasko/netty/ftp/FtpServerHandler activeSocket Ljava/net/Socket;
	invokevirtual java/net/Socket isClosed ()Z
	ifne L75
	ldc_w '503 Bad sequence of commands'
	aload_1
	ldc 'PORT'
	aload_2
	invokestatic com/alexkasko/netty/ftp/FtpServerHandler send [_163]
	goto L155
L75:
.stack same
	aload_0
	new java/net/Socket
	dup
	aload_3
	invokevirtual java/net/InetSocketAddress getAddress ()Ljava/net/InetAddress;
	aload_3
	invokevirtual java/net/InetSocketAddress getPort ()I
	invokespecial java/net/Socket <init> (Ljava/net/InetAddress;I)V
	putfield com/alexkasko/netty/ftp/FtpServerHandler activeSocket Ljava/net/Socket;
	ldc_w '200 PORT command successful'
	aload_1
	ldc 'PORT'
	aload_2
	invokestatic com/alexkasko/netty/ftp/FtpServerHandler send [_163]
L104:
	goto L155
L107:
.stack same_locals_1_stack_item
	stack Object java/io/IOException
.end stack
	astore 4
	getstatic com/alexkasko/netty/ftp/FtpServerHandler logger Lorg/slf4j/Logger;
	new java/lang/StringBuilder
	dup
	ldc_w [_330]
	invokespecial java/lang/StringBuilder <init> (Ljava/lang/String;)V
	aload_3
	invokevirtual java/lang/StringBuilder append (Ljava/lang/Object;)Ljava/lang/StringBuilder;
	ldc ']'
	invokevirtual java/lang/StringBuilder append (Ljava/lang/String;)Ljava/lang/StringBuilder;
	invokevirtual java/lang/StringBuilder toString ()Ljava/lang/String;
	aload 4
	invokeinterface org/slf4j/Logger warn (Ljava/lang/String;Ljava/lang/Throwable;)V 3
	aload_0
	invokespecial com/alexkasko/netty/ftp/FtpServerHandler closeActiveSocket ()V
	ldc_w '552 Requested file action aborted'
	aload_1
	ldc 'PORT'
	aload_2
	invokestatic com/alexkasko/netty/ftp/FtpServerHandler send [_163]
L155:
.stack same
	return
.end method

.method protected pasv : [_224]
.throws java/lang/InterruptedException
	.limit stack 6
	.limit locals 9
	.catch java/io/IOException from L44 to L152 using L155
	iconst_0
	istore_3
	goto L245
L5:
.stack append
	locals Integer
.end stack
	aload_0
	getfield com/alexkasko/netty/ftp/FtpServerHandler lowestPassivePort I
	aload_0
	getfield com/alexkasko/netty/ftp/FtpServerHandler highestPassivePort I
	invokestatic com/alexkasko/netty/ftp/FtpServerHandler choosePassivePort (II)I
	istore 4
	iload 4
	bipush 8
	ishr
	i2b
	sipush 255
	iand
	istore 5
	iload 4
	iconst_0
	ishr
	i2b
	sipush 255
	iand
	istore 6
	aconst_null
	astore 7
L44:
	aload_0
	getfield com/alexkasko/netty/ftp/FtpServerHandler passiveAddress [B
	invokestatic java/net/InetAddress getByAddress ([B)Ljava/net/InetAddress;
	astore 7
	aload_0
	new java/net/ServerSocket
	dup
	iload 4
	bipush 50
	aload 7
	invokespecial java/net/ServerSocket <init> (IILjava/net/InetAddress;)V
	putfield com/alexkasko/netty/ftp/FtpServerHandler passiveSocket Ljava/net/ServerSocket;
	ldc_w '227 Entering Passive Mode (%d,%d,%d,%d,%d,%d)'
	bipush 6
	anewarray java/lang/Object
	dup
	iconst_0
	aload_0
	getfield com/alexkasko/netty/ftp/FtpServerHandler passiveAddress [B
	iconst_0
	baload
	invokestatic java/lang/Byte valueOf (B)Ljava/lang/Byte;
	aastore
	dup
	iconst_1
	aload_0
	getfield com/alexkasko/netty/ftp/FtpServerHandler passiveAddress [B
	iconst_1
	baload
	invokestatic java/lang/Byte valueOf (B)Ljava/lang/Byte;
	aastore
	dup
	iconst_2
	aload_0
	getfield com/alexkasko/netty/ftp/FtpServerHandler passiveAddress [B
	iconst_2
	baload
	invokestatic java/lang/Byte valueOf (B)Ljava/lang/Byte;
	aastore
	dup
	iconst_3
	aload_0
	getfield com/alexkasko/netty/ftp/FtpServerHandler passiveAddress [B
	iconst_3
	baload
	invokestatic java/lang/Byte valueOf (B)Ljava/lang/Byte;
	aastore
	dup
	iconst_4
	iload 5
	invokestatic java/lang/Integer valueOf (I)Ljava/lang/Integer;
	aastore
	dup
	iconst_5
	iload 6
	invokestatic java/lang/Integer valueOf (I)Ljava/lang/Integer;
	aastore
	invokestatic java/lang/String format [_381]
	aload_1
	ldc 'PASV'
	aload_2
	invokestatic com/alexkasko/netty/ftp/FtpServerHandler send [_163]
L152:
	goto L253
L155:
.stack full
	locals Object com/alexkasko/netty/ftp/FtpServerHandler Object org/jboss/netty/channel/ChannelHandlerContext Object java/lang/String Integer Integer Integer Integer Object java/net/InetAddress
	stack Object java/io/IOException
.end stack
	astore 8
	getstatic com/alexkasko/netty/ftp/FtpServerHandler logger Lorg/slf4j/Logger;
	new java/lang/StringBuilder
	dup
	ldc_w [_382]
	invokespecial java/lang/StringBuilder <init> (Ljava/lang/String;)V
	aload 7
	invokevirtual java/lang/StringBuilder append (Ljava/lang/Object;)Ljava/lang/StringBuilder;
	ldc_w '], port: ['
	invokevirtual java/lang/StringBuilder append (Ljava/lang/String;)Ljava/lang/StringBuilder;
	iload 4
	invokevirtual java/lang/StringBuilder append (I)Ljava/lang/StringBuilder;
	ldc_w '], '
	invokevirtual java/lang/StringBuilder append (Ljava/lang/String;)Ljava/lang/StringBuilder;
	ldc_w 'attempt: ['
	invokevirtual java/lang/StringBuilder append (Ljava/lang/String;)Ljava/lang/StringBuilder;
	iload_3
	invokevirtual java/lang/StringBuilder append (I)Ljava/lang/StringBuilder;
	iconst_1
	invokevirtual java/lang/StringBuilder append (I)Ljava/lang/StringBuilder;
	ldc_w '] of: ['
	invokevirtual java/lang/StringBuilder append (Ljava/lang/String;)Ljava/lang/StringBuilder;
	aload_0
	getfield com/alexkasko/netty/ftp/FtpServerHandler passiveOpenAttempts I
	invokevirtual java/lang/StringBuilder append (I)Ljava/lang/StringBuilder;
	ldc ']'
	invokevirtual java/lang/StringBuilder append (Ljava/lang/String;)Ljava/lang/StringBuilder;
	invokevirtual java/lang/StringBuilder toString ()Ljava/lang/String;
	aload 8
	invokeinterface org/slf4j/Logger warn (Ljava/lang/String;Ljava/lang/Throwable;)V 3
	aload_0
	invokespecial com/alexkasko/netty/ftp/FtpServerHandler closePassiveSocket ()V
	lconst_1
	invokestatic java/lang/Thread sleep (J)V
	iinc 3 1
L245:
.stack full
	locals Object com/alexkasko/netty/ftp/FtpServerHandler Object org/jboss/netty/channel/ChannelHandlerContext Object java/lang/String Integer
	stack 
.end stack
	iload_3
	aload_0
	getfield com/alexkasko/netty/ftp/FtpServerHandler passiveOpenAttempts I
	if_icmplt L5
L253:
.stack chop 1
	aload_0
	getfield com/alexkasko/netty/ftp/FtpServerHandler passiveSocket Ljava/net/ServerSocket;
	ifnonnull L270
	ldc_w '551 Requested action aborted'
	aload_1
	ldc 'PASV'
	aload_2
	invokestatic com/alexkasko/netty/ftp/FtpServerHandler send [_163]
L270:
.stack same
	return
.end method

.method protected list : [_224]
	.limit stack 4
	.limit locals 6
	.catch java/io/IOException from L53 to L76 using L79
	.catch [0] from L53 to L124 using L131
	.catch java/io/IOException from L208 to L243 using L246
	.catch [0] from L208 to L309 using L316
	ldc 'PORT'
	aload_0
	getfield com/alexkasko/netty/ftp/FtpServerHandler lastCommand Ljava/lang/String;
	invokevirtual java/lang/String equals (Ljava/lang/Object;)Z
	ifeq L147
	aload_0
	getfield com/alexkasko/netty/ftp/FtpServerHandler activeSocket Ljava/net/Socket;
	ifnonnull L29
	ldc_w '503 Bad sequence of commands'
	aload_1
	ldc 'LIST'
	aload_2
	invokestatic com/alexkasko/netty/ftp/FtpServerHandler send [_163]
L29:
.stack same
	new java/lang/StringBuilder
	dup
	ldc_w [_408]
	invokespecial java/lang/StringBuilder <init> (Ljava/lang/String;)V
	aload_2
	invokevirtual java/lang/StringBuilder append (Ljava/lang/String;)Ljava/lang/StringBuilder;
	invokevirtual java/lang/StringBuilder toString ()Ljava/lang/String;
	aload_1
	ldc 'LIST'
	aload_2
	invokestatic com/alexkasko/netty/ftp/FtpServerHandler send [_163]
L53:
	aload_0
	getfield com/alexkasko/netty/ftp/FtpServerHandler activeSocket Ljava/net/Socket;
	invokevirtual java/net/Socket getOutputStream ()Ljava/io/OutputStream;
	getstatic com/alexkasko/netty/ftp/FtpServerHandler CRLF [B
	invokevirtual java/io/OutputStream write ([B)V
	ldc_w '226 Transfer complete for LIST'
	aload_1
	ldc ''
	aload_2
	invokestatic com/alexkasko/netty/ftp/FtpServerHandler send [_163]
L76:
	goto L140
L79:
.stack same_locals_1_stack_item
	stack Object java/io/IOException
.end stack
	astore_3
	getstatic com/alexkasko/netty/ftp/FtpServerHandler logger Lorg/slf4j/Logger;
	new java/lang/StringBuilder
	dup
	ldc_w [_422]
	invokespecial java/lang/StringBuilder <init> (Ljava/lang/String;)V
	aload_0
	getfield com/alexkasko/netty/ftp/FtpServerHandler activeSocket Ljava/net/Socket;
	invokevirtual java/lang/StringBuilder append (Ljava/lang/Object;)Ljava/lang/StringBuilder;
	ldc ']'
	invokevirtual java/lang/StringBuilder append (Ljava/lang/String;)Ljava/lang/StringBuilder;
	invokevirtual java/lang/StringBuilder toString ()Ljava/lang/String;
	aload_3
	invokeinterface org/slf4j/Logger warn (Ljava/lang/String;Ljava/lang/Throwable;)V 3
	ldc_w '552 Requested file action aborted'
	aload_1
	ldc 'LIST'
	aload_2
	invokestatic com/alexkasko/netty/ftp/FtpServerHandler send [_163]
L124:
	aload_0
	invokespecial com/alexkasko/netty/ftp/FtpServerHandler closeActiveSocket ()V
	goto L342
L131:
.stack same_locals_1_stack_item
	stack Object java/lang/Throwable
.end stack
	astore 4
	aload_0
	invokespecial com/alexkasko/netty/ftp/FtpServerHandler closeActiveSocket ()V
	aload 4
	athrow
L140:
.stack same
	aload_0
	invokespecial com/alexkasko/netty/ftp/FtpServerHandler closeActiveSocket ()V
.stack same
	goto L342
L147:
.stack same
	ldc 'PASV'
	aload_0
	getfield com/alexkasko/netty/ftp/FtpServerHandler lastCommand Ljava/lang/String;
	invokevirtual java/lang/String equals (Ljava/lang/Object;)Z
	ifeq L332
	aload_0
	getfield com/alexkasko/netty/ftp/FtpServerHandler passiveSocket Ljava/net/ServerSocket;
	ifnonnull L176
	ldc_w '503 Bad sequence of commands'
	aload_1
	ldc 'LIST'
	aload_2
	invokestatic com/alexkasko/netty/ftp/FtpServerHandler send [_163]
L176:
.stack same
	new java/lang/StringBuilder
	dup
	ldc_w [_424]
	invokespecial java/lang/StringBuilder <init> (Ljava/lang/String;)V
	aload_0
	getfield com/alexkasko/netty/ftp/FtpServerHandler passiveSocket Ljava/net/ServerSocket;
	invokevirtual java/net/ServerSocket getLocalPort ()I
	invokevirtual java/lang/StringBuilder append (I)Ljava/lang/StringBuilder;
	invokevirtual java/lang/StringBuilder toString ()Ljava/lang/String;
	aload_1
	ldc 'LIST'
	aload_2
	invokestatic com/alexkasko/netty/ftp/FtpServerHandler send [_163]
	aconst_null
	astore_3
L208:
	aload_0
	getfield com/alexkasko/netty/ftp/FtpServerHandler passiveSocket Ljava/net/ServerSocket;
	invokevirtual java/net/ServerSocket accept ()Ljava/net/Socket;
	astore_3
	aload_3
	invokevirtual java/net/Socket getOutputStream ()Ljava/io/OutputStream;
	getstatic com/alexkasko/netty/ftp/FtpServerHandler CRLF [B
	invokevirtual java/io/OutputStream write ([B)V
	aload_3
	invokevirtual java/net/Socket getOutputStream ()Ljava/io/OutputStream;
	invokevirtual java/io/OutputStream close ()V
	ldc_w '226 Transfer complete for LIST'
	aload_1
	ldc ''
	aload_2
	invokestatic com/alexkasko/netty/ftp/FtpServerHandler send [_163]
L243:
	goto L325
L246:
.stack full
	locals Object com/alexkasko/netty/ftp/FtpServerHandler Object org/jboss/netty/channel/ChannelHandlerContext Object java/lang/String Object java/net/Socket
	stack Object java/io/IOException
.end stack
	astore 4
	getstatic com/alexkasko/netty/ftp/FtpServerHandler logger Lorg/slf4j/Logger;
	new java/lang/StringBuilder
	dup
	ldc_w [_436]
	invokespecial java/lang/StringBuilder <init> (Ljava/lang/String;)V
	aload_0
	getfield com/alexkasko/netty/ftp/FtpServerHandler passiveSocket Ljava/net/ServerSocket;
	invokevirtual java/lang/StringBuilder append (Ljava/lang/Object;)Ljava/lang/StringBuilder;
	ldc_w '],'
	invokevirtual java/lang/StringBuilder append (Ljava/lang/String;)Ljava/lang/StringBuilder;
	ldc_w 'accepted client socket: ['
	invokevirtual java/lang/StringBuilder append (Ljava/lang/String;)Ljava/lang/StringBuilder;
	aload_3
	invokevirtual java/lang/StringBuilder append (Ljava/lang/Object;)Ljava/lang/StringBuilder;
	ldc ']'
	invokevirtual java/lang/StringBuilder append (Ljava/lang/String;)Ljava/lang/StringBuilder;
	invokevirtual java/lang/StringBuilder toString ()Ljava/lang/String;
	aload 4
	invokeinterface org/slf4j/Logger warn (Ljava/lang/String;Ljava/lang/Throwable;)V 3
	ldc_w '552 Requested file action aborted'
	aload_1
	ldc 'LIST'
	aload_2
	invokestatic com/alexkasko/netty/ftp/FtpServerHandler send [_163]
L309:
	aload_0
	invokespecial com/alexkasko/netty/ftp/FtpServerHandler closePassiveSocket ()V
	goto L342
L316:
.stack same_locals_1_stack_item_extended
	stack Object java/lang/Throwable
.end stack
	astore 5
	aload_0
	invokespecial com/alexkasko/netty/ftp/FtpServerHandler closePassiveSocket ()V
	aload 5
	athrow
L325:
.stack same
	aload_0
	invokespecial com/alexkasko/netty/ftp/FtpServerHandler closePassiveSocket ()V
.stack chop 1
	goto L342
L332:
.stack same
	ldc_w '503 Bad sequence of commands'
	aload_1
	ldc 'LIST'
	aload_2
	invokestatic com/alexkasko/netty/ftp/FtpServerHandler send [_163]
L342:
.stack same
	return
.end method

.method protected stor : [_224]
	.limit stack 4
	.limit locals 6
	.catch java/io/IOException from L53 to L94 using L97
	.catch [0] from L53 to L142 using L149
	.catch java/io/IOException from L220 to L266 using L269
	.catch [0] from L220 to L332 using L339
	ldc 'PORT'
	aload_0
	getfield com/alexkasko/netty/ftp/FtpServerHandler lastCommand Ljava/lang/String;
	invokevirtual java/lang/String equals (Ljava/lang/Object;)Z
	ifeq L165
	aload_0
	getfield com/alexkasko/netty/ftp/FtpServerHandler activeSocket Ljava/net/Socket;
	ifnonnull L29
	ldc_w '503 Bad sequence of commands'
	aload_1
	ldc 'STOR'
	aload_2
	invokestatic com/alexkasko/netty/ftp/FtpServerHandler send [_163]
L29:
.stack same
	new java/lang/StringBuilder
	dup
	ldc_w '150 Opening binary mode data connection for '
	invokespecial java/lang/StringBuilder <init> (Ljava/lang/String;)V
	aload_2
	invokevirtual java/lang/StringBuilder append (Ljava/lang/String;)Ljava/lang/StringBuilder;
	invokevirtual java/lang/StringBuilder toString ()Ljava/lang/String;
	aload_1
	ldc ''
	aload_2
	invokestatic com/alexkasko/netty/ftp/FtpServerHandler send [_163]
L53:
	aload_0
	getfield com/alexkasko/netty/ftp/FtpServerHandler receiver Lcom/alexkasko/netty/ftp/DataReceiver;
	aload_2
	aload_0
	getfield com/alexkasko/netty/ftp/FtpServerHandler activeSocket Ljava/net/Socket;
	invokevirtual java/net/Socket getInputStream ()Ljava/io/InputStream;
	invokeinterface com/alexkasko/netty/ftp/DataReceiver receive (Ljava/lang/String;Ljava/io/InputStream;)V 3
	new java/lang/StringBuilder
	dup
	ldc_w '226 Transfer complete for STOR '
	invokespecial java/lang/StringBuilder <init> (Ljava/lang/String;)V
	aload_2
	invokevirtual java/lang/StringBuilder append (Ljava/lang/String;)Ljava/lang/StringBuilder;
	invokevirtual java/lang/StringBuilder toString ()Ljava/lang/String;
	aload_1
	ldc ''
	aload_2
	invokestatic com/alexkasko/netty/ftp/FtpServerHandler send [_163]
L94:
	goto L158
L97:
.stack same_locals_1_stack_item_extended
	stack Object java/io/IOException
.end stack
	astore_3
	getstatic com/alexkasko/netty/ftp/FtpServerHandler logger Lorg/slf4j/Logger;
	new java/lang/StringBuilder
	dup
	ldc_w [_455]
	invokespecial java/lang/StringBuilder <init> (Ljava/lang/String;)V
	aload_0
	getfield com/alexkasko/netty/ftp/FtpServerHandler activeSocket Ljava/net/Socket;
	invokevirtual java/lang/StringBuilder append (Ljava/lang/Object;)Ljava/lang/StringBuilder;
	ldc ']'
	invokevirtual java/lang/StringBuilder append (Ljava/lang/String;)Ljava/lang/StringBuilder;
	invokevirtual java/lang/StringBuilder toString ()Ljava/lang/String;
	aload_3
	invokeinterface org/slf4j/Logger warn (Ljava/lang/String;Ljava/lang/Throwable;)V 3
	ldc_w '552 Requested file action aborted'
	aload_1
	ldc 'STOR'
	aload_2
	invokestatic com/alexkasko/netty/ftp/FtpServerHandler send [_163]
L142:
	aload_0
	invokespecial com/alexkasko/netty/ftp/FtpServerHandler closeActiveSocket ()V
	goto L365
L149:
.stack same_locals_1_stack_item
	stack Object java/lang/Throwable
.end stack
	astore 4
	aload_0
	invokespecial com/alexkasko/netty/ftp/FtpServerHandler closeActiveSocket ()V
	aload 4
	athrow
L158:
.stack same
	aload_0
	invokespecial com/alexkasko/netty/ftp/FtpServerHandler closeActiveSocket ()V
.stack same
	goto L365
L165:
.stack same
	ldc 'PASV'
	aload_0
	getfield com/alexkasko/netty/ftp/FtpServerHandler lastCommand Ljava/lang/String;
	invokevirtual java/lang/String equals (Ljava/lang/Object;)Z
	ifeq L355
	aload_0
	getfield com/alexkasko/netty/ftp/FtpServerHandler passiveSocket Ljava/net/ServerSocket;
	ifnonnull L194
	ldc_w '503 Bad sequence of commands'
	aload_1
	ldc 'STOR'
	aload_2
	invokestatic com/alexkasko/netty/ftp/FtpServerHandler send [_163]
L194:
.stack same
	new java/lang/StringBuilder
	dup
	ldc_w '150 Opening binary mode data connection for '
	invokespecial java/lang/StringBuilder <init> (Ljava/lang/String;)V
	aload_2
	invokevirtual java/lang/StringBuilder append (Ljava/lang/String;)Ljava/lang/StringBuilder;
	invokevirtual java/lang/StringBuilder toString ()Ljava/lang/String;
	aload_1
	ldc 'STOR'
	aload_2
	invokestatic com/alexkasko/netty/ftp/FtpServerHandler send [_163]
	aconst_null
	astore_3
L220:
	aload_0
	getfield com/alexkasko/netty/ftp/FtpServerHandler passiveSocket Ljava/net/ServerSocket;
	invokevirtual java/net/ServerSocket accept ()Ljava/net/Socket;
	astore_3
	aload_0
	getfield com/alexkasko/netty/ftp/FtpServerHandler receiver Lcom/alexkasko/netty/ftp/DataReceiver;
	aload_2
	aload_3
	invokevirtual java/net/Socket getInputStream ()Ljava/io/InputStream;
	invokeinterface com/alexkasko/netty/ftp/DataReceiver receive (Ljava/lang/String;Ljava/io/InputStream;)V 3
	new java/lang/StringBuilder
	dup
	ldc_w '226 Transfer complete for STOR '
	invokespecial java/lang/StringBuilder <init> (Ljava/lang/String;)V
	aload_2
	invokevirtual java/lang/StringBuilder append (Ljava/lang/String;)Ljava/lang/StringBuilder;
	invokevirtual java/lang/StringBuilder toString ()Ljava/lang/String;
	aload_1
	ldc ''
	aload_2
	invokestatic com/alexkasko/netty/ftp/FtpServerHandler send [_163]
L266:
	goto L348
L269:
.stack full
	locals Object com/alexkasko/netty/ftp/FtpServerHandler Object org/jboss/netty/channel/ChannelHandlerContext Object java/lang/String Object java/net/Socket
	stack Object java/io/IOException
.end stack
	astore 4
	getstatic com/alexkasko/netty/ftp/FtpServerHandler logger Lorg/slf4j/Logger;
	new java/lang/StringBuilder
	dup
	ldc_w [_457]
	invokespecial java/lang/StringBuilder <init> (Ljava/lang/String;)V
	aload_0
	getfield com/alexkasko/netty/ftp/FtpServerHandler passiveSocket Ljava/net/ServerSocket;
	invokevirtual java/lang/StringBuilder append (Ljava/lang/Object;)Ljava/lang/StringBuilder;
	ldc_w '], '
	invokevirtual java/lang/StringBuilder append (Ljava/lang/String;)Ljava/lang/StringBuilder;
	ldc_w 'accepted client socket: ['
	invokevirtual java/lang/StringBuilder append (Ljava/lang/String;)Ljava/lang/StringBuilder;
	aload_3
	invokevirtual java/lang/StringBuilder append (Ljava/lang/Object;)Ljava/lang/StringBuilder;
	ldc ']'
	invokevirtual java/lang/StringBuilder append (Ljava/lang/String;)Ljava/lang/StringBuilder;
	invokevirtual java/lang/StringBuilder toString ()Ljava/lang/String;
	aload 4
	invokeinterface org/slf4j/Logger warn (Ljava/lang/String;Ljava/lang/Throwable;)V 3
	ldc_w '552 Requested file action aborted'
	aload_1
	ldc 'STOR'
	aload_2
	invokestatic com/alexkasko/netty/ftp/FtpServerHandler send [_163]
L332:
	aload_0
	invokespecial com/alexkasko/netty/ftp/FtpServerHandler closePassiveSocket ()V
	goto L365
L339:
.stack same_locals_1_stack_item_extended
	stack Object java/lang/Throwable
.end stack
	astore 5
	aload_0
	invokespecial com/alexkasko/netty/ftp/FtpServerHandler closePassiveSocket ()V
	aload 5
	athrow
L348:
.stack same
	aload_0
	invokespecial com/alexkasko/netty/ftp/FtpServerHandler closePassiveSocket ()V
.stack chop 1
	goto L365
L355:
.stack same
	ldc_w '503 Bad sequence of commands'
	aload_1
	ldc 'STOR'
	aload_2
	invokestatic com/alexkasko/netty/ftp/FtpServerHandler send [_163]
L365:
.stack same
	return
.end method

.method static private send : [_163]
	.limit stack 4
	.limit locals 6
	getstatic com/alexkasko/netty/ftp/FtpServerHandler logger Lorg/slf4j/Logger;
	invokeinterface org/slf4j/Logger isDebugEnabled ()Z 1
	ifeq L78
	aload_2
	invokevirtual java/lang/String length ()I
	ifle L53
	getstatic com/alexkasko/netty/ftp/FtpServerHandler logger Lorg/slf4j/Logger;
	new java/lang/StringBuilder
	dup
	ldc_w '-> '
	invokespecial java/lang/StringBuilder <init> (Ljava/lang/String;)V
	aload_2
	invokevirtual java/lang/StringBuilder append (Ljava/lang/String;)Ljava/lang/StringBuilder;
	ldc_w ' '
	invokevirtual java/lang/StringBuilder append (Ljava/lang/String;)Ljava/lang/StringBuilder;
	aload_3
	invokevirtual java/lang/StringBuilder append (Ljava/lang/String;)Ljava/lang/StringBuilder;
	invokevirtual java/lang/StringBuilder toString ()Ljava/lang/String;
	invokeinterface org/slf4j/Logger debug (Ljava/lang/String;)V 2
L53:
.stack same
	getstatic com/alexkasko/netty/ftp/FtpServerHandler logger Lorg/slf4j/Logger;
	new java/lang/StringBuilder
	dup
	ldc_w '<- '
	invokespecial java/lang/StringBuilder <init> (Ljava/lang/String;)V
	aload_0
	invokevirtual java/lang/StringBuilder append (Ljava/lang/String;)Ljava/lang/StringBuilder;
	invokevirtual java/lang/StringBuilder toString ()Ljava/lang/String;
	invokeinterface org/slf4j/Logger debug (Ljava/lang/String;)V 2
L78:
.stack same
	new java/lang/StringBuilder
	dup
	aload_0
	invokestatic java/lang/String valueOf (Ljava/lang/Object;)Ljava/lang/String;
	invokespecial java/lang/StringBuilder <init> (Ljava/lang/String;)V
	ldc_w '\r\n'
	invokevirtual java/lang/StringBuilder append (Ljava/lang/String;)Ljava/lang/StringBuilder;
	invokevirtual java/lang/StringBuilder toString ()Ljava/lang/String;
	astore 4
	aload 4
	getstatic com/alexkasko/netty/ftp/FtpServerHandler ASCII Ljava/nio/charset/Charset;
	invokevirtual java/lang/String getBytes (Ljava/nio/charset/Charset;)[B
	astore 5
	aload_1
	invokeinterface org/jboss/netty/channel/ChannelHandlerContext getChannel ()Lorg/jboss/netty/channel/Channel; 1
	aload 5
	invokestatic org/jboss/netty/buffer/ChannelBuffers wrappedBuffer ([B)Lorg/jboss/netty/buffer/ChannelBuffer;
	invokeinterface org/jboss/netty/channel/Channel write [_491] 2
	pop
	return
.end method

.method static private parsePortArgs : (Ljava/lang/String;)Ljava/net/InetSocketAddress;
	.limit stack 4
	.limit locals 6
	.catch java/lang/NumberFormatException from L32 to L43 using L46
	.catch java/net/UnknownHostException from L114 to L120 using L123
	aload_0
	ldc_w ','
	invokevirtual java/lang/String split (Ljava/lang/String;)[Ljava/lang/String;
	astore_1
	aload_1
	arraylength
	bipush 6
	if_icmpeq L17
	aconst_null
	areturn
L17:
.stack append
	locals Object [Ljava/lang/String;
.end stack
	iconst_4
	newarray byte
	astore_2
	bipush 6
	newarray int
	astore_3
	iconst_0
	istore 4
	goto L71
L32:
.stack append
	locals Object [B Object [I Integer
.end stack
	aload_3
	iload 4
	aload_1
	iload 4
	aaload
	invokestatic java/lang/Integer parseInt (Ljava/lang/String;)I
	iastore
L43:
	goto L49
L46:
.stack same_locals_1_stack_item
	stack Object java/lang/NumberFormatException
.end stack
	pop
	aconst_null
	areturn
L49:
.stack same
	aload_3
	iload 4
	iaload
	iflt L66
	aload_3
	iload 4
	iaload
	sipush 255
	if_icmple L68
L66:
.stack same
	aconst_null
	areturn
L68:
.stack same
	iinc 4 1
L71:
.stack same
	iload 4
	bipush 6
	if_icmplt L32
	iconst_0
	istore 4
	goto L96
L84:
.stack same
	aload_2
	iload 4
	aload_3
	iload 4
	iaload
	i2b
	bastore
	iinc 4 1
L96:
.stack same
	iload 4
	iconst_4
	if_icmplt L84
	aload_3
	iconst_4
	iaload
	bipush 8
	ishl
	aload_3
	iconst_5
	iaload
	ior
	istore 4
L114:
	aload_2
	invokestatic java/net/InetAddress getByAddress ([B)Ljava/net/InetAddress;
	astore 5
L120:
	goto L126
L123:
.stack same_locals_1_stack_item
	stack Object java/net/UnknownHostException
.end stack
	pop
	aconst_null
	areturn
L126:
.stack append
	locals Object java/net/InetAddress
.end stack
	new java/net/InetSocketAddress
	dup
	aload 5
	iload 4
	invokespecial java/net/InetSocketAddress <init> (Ljava/net/InetAddress;I)V
	areturn
.end method

.method static private choosePassivePort : (II)I
	.limit stack 4
	.limit locals 4
	iload_1
	iload_0
	isub
	istore_2
	invokestatic java/lang/System currentTimeMillis ()J
	iload_2
	i2l
	lrem
	l2i
	istore_3
	iload_0
	iload_3
	iadd
	ireturn
.end method

.method private closeActiveSocket : ()V
	.limit stack 3
	.limit locals 3
	.catch java/lang/Exception from L8 to L15 using L18
	.catch [0] from L8 to L31 using L39
	aload_0
	getfield com/alexkasko/netty/ftp/FtpServerHandler activeSocket Ljava/net/Socket;
	ifnonnull L8
	return
L8:
.stack same
	aload_0
	getfield com/alexkasko/netty/ftp/FtpServerHandler activeSocket Ljava/net/Socket;
	invokevirtual java/net/Socket close ()V
L15:
	goto L47
L18:
.stack same_locals_1_stack_item
	stack Object java/lang/Exception
.end stack
	astore_1
	getstatic com/alexkasko/netty/ftp/FtpServerHandler logger Lorg/slf4j/Logger;
	ldc_w 'Exception thrown on closing active socket'
	aload_1
	invokeinterface org/slf4j/Logger warn (Ljava/lang/String;Ljava/lang/Throwable;)V 3
L31:
	aload_0
	aconst_null
	putfield com/alexkasko/netty/ftp/FtpServerHandler activeSocket Ljava/net/Socket;
	goto L52
L39:
.stack same_locals_1_stack_item
	stack Object java/lang/Throwable
.end stack
	astore_2
	aload_0
	aconst_null
	putfield com/alexkasko/netty/ftp/FtpServerHandler activeSocket Ljava/net/Socket;
	aload_2
	athrow
L47:
.stack same
	aload_0
	aconst_null
	putfield com/alexkasko/netty/ftp/FtpServerHandler activeSocket Ljava/net/Socket;
L52:
.stack same
	return
.end method

.method private closePassiveSocket : ()V
	.limit stack 3
	.limit locals 3
	.catch java/lang/Exception from L8 to L15 using L18
	.catch [0] from L8 to L31 using L39
	aload_0
	getfield com/alexkasko/netty/ftp/FtpServerHandler passiveSocket Ljava/net/ServerSocket;
	ifnonnull L8
	return
L8:
.stack same
	aload_0
	getfield com/alexkasko/netty/ftp/FtpServerHandler passiveSocket Ljava/net/ServerSocket;
	invokevirtual java/net/ServerSocket close ()V
L15:
	goto L47
L18:
.stack same_locals_1_stack_item
	stack Object java/lang/Exception
.end stack
	astore_1
	getstatic com/alexkasko/netty/ftp/FtpServerHandler logger Lorg/slf4j/Logger;
	ldc_w 'Exception thrown on closing server socket'
	aload_1
	invokeinterface org/slf4j/Logger warn (Ljava/lang/String;Ljava/lang/Throwable;)V 3
L31:
	aload_0
	aconst_null
	putfield com/alexkasko/netty/ftp/FtpServerHandler passiveSocket Ljava/net/ServerSocket;
	goto L52
L39:
.stack same_locals_1_stack_item
	stack Object java/lang/Throwable
.end stack
	astore_2
	aload_0
	aconst_null
	putfield com/alexkasko/netty/ftp/FtpServerHandler passiveSocket Ljava/net/ServerSocket;
	aload_2
	athrow
L47:
.stack same
	aload_0
	aconst_null
	putfield com/alexkasko/netty/ftp/FtpServerHandler passiveSocket Ljava/net/ServerSocket;
L52:
.stack same
	return
.end method

.const [_1] = Class com/alexkasko/netty/ftp/FtpServerHandler
.const [_3] = Class [_4]
.const [_4] = Utf8 org/jboss/netty/channel/SimpleChannelUpstreamHandler
.const [_62] = Utf8 (Lcom/alexkasko/netty/ftp/DataReceiver;Ljava/net/InetAddress;III)V
.const [_139] = Utf8 (Lorg/jboss/netty/channel/ChannelHandlerContext;Lorg/jboss/netty/channel/MessageEvent;)V
.const [_163] = Utf8 (Ljava/lang/String;Lorg/jboss/netty/channel/ChannelHandlerContext;Ljava/lang/String;Ljava/lang/String;)V
.const [_224] = Utf8 (Lorg/jboss/netty/channel/ChannelHandlerContext;Ljava/lang/String;)V
.const [_255] = Utf8 (Lorg/jboss/netty/channel/ChannelHandlerContext;Lorg/jboss/netty/channel/ExceptionEvent;)V
.const [_278] = Utf8 (Lorg/jboss/netty/channel/ChannelHandlerContext;Lorg/jboss/netty/channel/ChannelStateEvent;)V
.const [_330] = String [_331]
.const [_331] = Utf8 'Exception thrown on opening active socket to address: ['
.const [_381] = Utf8 (Ljava/lang/String;[Ljava/lang/Object;)Ljava/lang/String;
.const [_382] = String [_383]
.const [_383] = Utf8 'Exception thrown on binding passive socket to address: ['
.const [_408] = String [_409]
.const [_409] = Utf8 '150 Opening binary mode data connection for LIST '
.const [_422] = String [_423]
.const [_423] = Utf8 'Exception thrown on writing through active socket: ['
.const [_424] = String [_425]
.const [_425] = Utf8 '150 Opening binary mode data connection for LIST on port: '
.const [_436] = String [_437]
.const [_437] = Utf8 'Exception thrown on writing through passive socket: ['
.const [_455] = String [_456]
.const [_456] = Utf8 'Exception thrown on reading through active socket: ['
.const [_457] = String [_458]
.const [_458] = Utf8 'Exception thrown on reading through passive socket: ['
.const [_491] = Utf8 (Ljava/lang/Object;)Lorg/jboss/netty/channel/ChannelFuture;